pyarmor/cli/core/linux/__init__.py
pyarmor/cli/core/linux/aarch64/pyarmor_runtime.so
pyarmor/cli/core/linux/aarch64/pytransform3.so
pyarmor/cli/core/linux/armv7/pyarmor_runtime.so
pyarmor/cli/core/linux/armv7/pytransform3.so
pyarmor/cli/core/linux/loongarch64/pyarmor_runtime.so
pyarmor/cli/core/linux/loongarch64/pytransform3.so
pyarmor/cli/core/linux/mips32el/pyarmor_runtime.so
pyarmor/cli/core/linux/mips32el/pytransform3.so
pyarmor/cli/core/linux/mips64el/pyarmor_runtime.so
pyarmor/cli/core/linux/mips64el/pytransform3.so
pyarmor/cli/core/linux/ppc64le/pyarmor_runtime.so
pyarmor/cli/core/linux/ppc64le/pytransform3.so
pyarmor/cli/core/linux/x86/pyarmor_runtime.so
pyarmor/cli/core/linux/x86/pytransform3.so
pyarmor/cli/core/linux/x86_64/pyarmor_runtime.so
pyarmor/cli/core/linux/x86_64/pytransform3.so
pyarmor_cli_core_linux-7.6.8.dist-info/METADATA
pyarmor_cli_core_linux-7.6.8.dist-info/WHEEL
pyarmor_cli_core_linux-7.6.8.dist-info/top_level.txt
pyarmor_cli_core_linux-7.6.8.dist-info/RECORD
